gsql_client/__init__.py
gsql_client/common.py
gsql_client/gsql.py
gsql_client/restpp.py
gsql_client-0.1.6.dist-info/LICENSE
gsql_client-0.1.6.dist-info/METADATA
gsql_client-0.1.6.dist-info/WHEEL
gsql_client-0.1.6.dist-info/top_level.txt
gsql_client-0.1.6.dist-info/RECORD
