Metadata-Version: 2.1
Name: gsql-client
Version: 0.1.6
Summary: GSQL and RESTPP Python remote clients for TigerGraph
Home-page: https://github.com/dingmaotu/gsql_client
Author: Ding Li
Author-email: dingmaotu@hotmail.com
License: UNKNOWN
Keywords: tigergraph,gsql,restpp,client
Platform: UNKNOWN
Classifier: Development Status :: 4 - Beta
Classifier: Programming Language :: Python :: 2
Classifier: Programming Language :: Python :: 3
Classifier: License :: OSI Approved :: MIT License
Classifier: Operating System :: OS Independent
Classifier: Topic :: Database :: Front-Ends
Requires-Python: >=2.7
